tag_publish/__init__.py
tag_publish/cli.py
tag_publish/configuration.py
tag_publish/lib/__init__.py
tag_publish/lib/docker.py
tag_publish/lib/oidc.py
tag_publish/new.py
tag_publish/publish.py
tag_publish/py.typed
tag_publish/schema.json
tag_publish/versions.yaml
tag_publish-1.1.1.dist-info/LICENSE
tag_publish-1.1.1.dist-info/METADATA
tag_publish-1.1.1.dist-info/WHEEL
tag_publish-1.1.1.dist-info/entry_points.txt
tag_publish-1.1.1.dist-info/RECORD
