Metadata-Version: 2.3
Name: tag-publish
Version: 1.1.1
Summary: Tools used to publish Python packages, Docker images and Helm charts for GitHub tag and branch
License: FreeBSD
Keywords: ci
Author: Camptocamp
Author-email: info@camptocamp.com
Requires-Python: >=3.9
Classifier: Development Status :: 5 - Production/Stable
Classifier: Environment :: Console
Classifier: Intended Audience :: Developers
Classifier: License :: OSI Approved :: MIT License
Classifier: Operating System :: OS Independent
Classifier: Programming Language :: Python
Classifier: Programming Language :: Python :: 3
Classifier: Programming Language :: Python :: 3.9
Classifier: Programming Language :: Python :: 3.10
Classifier: Programming Language :: Python :: 3.11
Classifier: Programming Language :: Python :: 3.12
Classifier: Programming Language :: Python :: 3.13
Classifier: Typing :: Typed
Requires-Dist: PyYAML (>=6,<7)
Requires-Dist: applications-download (>=1,<2)
Requires-Dist: debian-inspector (>=31,<32)
Requires-Dist: githubkit (>=0,<1)
Requires-Dist: id (>=1,<2)
Requires-Dist: jsonschema-validator-new (>=0,<1)
Requires-Dist: multi-repo-automation (>=1,<2)
Requires-Dist: requests (>=2,<3)
Requires-Dist: security-md (>=1,<2)
Requires-Dist: twine (>=6,<7)
Project-URL: Bug Tracker, https://github.com/camptocamp/tag-publish/issues
Project-URL: Repository, https://github.com/camptocamp/tag-publish
